mlregression/__init__.py
mlregression/mlreg.py
mlregression/base/__init__.py
mlregression/base/base_mlreg.py
mlregression/estimator/__init__.py
mlregression/estimator/boosting.py
mlregression/utils/__init__.py
mlregression/utils/data.py
mlregression/utils/exceptions.py
mlregression/utils/model_params.py
mlregression/utils/sanity_check.py
mlregression/utils/tools.py
mlregression-0.1.9.dist-info/LICENSE
mlregression-0.1.9.dist-info/METADATA
mlregression-0.1.9.dist-info/WHEEL
mlregression-0.1.9.dist-info/top_level.txt
mlregression-0.1.9.dist-info/RECORD
