Metadata-Version: 2.1
Name: mlregression
Version: 0.1.9
Summary: Machine learning regression off-the-shelf
Home-page: https://github.com/muhlbach/mlregression
Author: Nicolaj Søndergaard Mühlbach
Author-email: n.muhlbach@gmail.com
License: MIT License
Keywords: machine learning,regression,tuning
Platform: UNKNOWN
Classifier: Programming Language :: Python :: 3
Classifier: License :: OSI Approved :: MIT License
Classifier: Operating System :: OS Independent
Requires-Python: >=3.6
License-File: LICENSE
